langgraph_agent_toolkit/__init__.py
langgraph_agent_toolkit/run_api.py
langgraph_agent_toolkit/run_app.py
langgraph_agent_toolkit/agents/__init__.py
langgraph_agent_toolkit/agents/agent.py
langgraph_agent_toolkit/agents/agent_executor.py
langgraph_agent_toolkit/agents/blueprints/__init__.py
langgraph_agent_toolkit/agents/blueprints/bg_task_agent/__init__.py
langgraph_agent_toolkit/agents/blueprints/bg_task_agent/agent.py
langgraph_agent_toolkit/agents/blueprints/bg_task_agent/task.py
langgraph_agent_toolkit/agents/blueprints/bg_task_agent/utils.py
langgraph_agent_toolkit/agents/blueprints/chatbot/__init__.py
langgraph_agent_toolkit/agents/blueprints/chatbot/agent.py
langgraph_agent_toolkit/agents/blueprints/command_agent/__init__.py
langgraph_agent_toolkit/agents/blueprints/command_agent/agent.py
langgraph_agent_toolkit/agents/blueprints/interrupt_agent/__init__.py
langgraph_agent_toolkit/agents/blueprints/interrupt_agent/agent.py
langgraph_agent_toolkit/agents/blueprints/knowledge_base_agent/__init__.py
langgraph_agent_toolkit/agents/blueprints/knowledge_base_agent/agent.py
langgraph_agent_toolkit/agents/blueprints/react/__init__.py
langgraph_agent_toolkit/agents/blueprints/react/agent.py
langgraph_agent_toolkit/agents/blueprints/react_new/__init__.py
langgraph_agent_toolkit/agents/blueprints/react_new/agent.py
langgraph_agent_toolkit/agents/blueprints/react_old/__init__.py
langgraph_agent_toolkit/agents/blueprints/react_old/agent.py
langgraph_agent_toolkit/agents/blueprints/react_so/__init__.py
langgraph_agent_toolkit/agents/blueprints/react_so/agent.py
langgraph_agent_toolkit/agents/blueprints/react_so_old/__init__.py
langgraph_agent_toolkit/agents/blueprints/react_so_old/agent.py
langgraph_agent_toolkit/agents/blueprints/supervisor_agent/__init__.py
langgraph_agent_toolkit/agents/blueprints/supervisor_agent/agent.py
langgraph_agent_toolkit/agents/components/__init__.py
langgraph_agent_toolkit/agents/components/tools.py
langgraph_agent_toolkit-0.8.14.dist-info/METADATA
langgraph_agent_toolkit-0.8.14.dist-info/WHEEL
langgraph_agent_toolkit-0.8.14.dist-info/licenses/LICENSE
langgraph_agent_toolkit-0.8.14.dist-info/RECORD
