Metadata-Version: 2.4
Name: langgraph-agent-toolkit
Version: 0.8.14
Summary: Full toolkit for running an AI agent service built with LangGraph, FastAPI and Streamlit
Project-URL: documentation, https://kryvokhyzha.github.io/langgraph-agent-toolkit
Project-URL: repository, https://github.com/kryvokhyzha/langgraph-agent-toolkit
Project-URL: PyPI, https://pypi.org/project/langgraph-agent-toolkit
Author-email: Roman Kryvokhyzha <kriwohizha@gmail.com>, Joshua Carroll <carroll.joshk@gmail.com>
License-Expression: MIT
License-File: LICENSE
Keywords: agents,blueprint,fastapi,langgraph,litellm,streamlit
Classifier: Development Status :: 4 - Beta
Classifier: Framework :: FastAPI
Classifier: License :: OSI Approved :: MIT License
Classifier: Operating System :: OS Independent
Classifier: Programming Language :: Python :: 3.11
Classifier: Programming Language :: Python :: 3.12
Classifier: Programming Language :: Python :: 3.13
Classifier: Topic :: Scientific/Engineering
Classifier: Topic :: Scientific/Engineering :: Artificial Intelligence
Classifier: Topic :: Software Development
Classifier: Topic :: Software Development :: Libraries :: Python Modules
Requires-Python: <3.14,>=3.11
Requires-Dist: ddgs>=9.5.0
Requires-Dist: duckduckgo-search>=7.3.0
Requires-Dist: fastapi<0.122.0,>=0.116.1
Requires-Dist: fire~=0.7.0
Requires-Dist: grpcio>=1.68.0
Requires-Dist: httpx~=0.28.1
Requires-Dist: jinja2~=3.1.6
Requires-Dist: jiter<0.13,>=0.10
Requires-Dist: joblib>=1.4.2
Requires-Dist: langchain-community<0.4.2,>=0.3.20
Requires-Dist: langchain-core<1.2.2,>=0.3.40
Requires-Dist: langchain<1.2.1,>=0.3.20
Requires-Dist: langgraph-checkpoint-postgres<3.0.2,>=3.0.0
Requires-Dist: langgraph-checkpoint-sqlite<3.0.1,>=3.0.0
Requires-Dist: langgraph-cli[inmem]<0.5.0,>=0.2.10
Requires-Dist: langgraph-supervisor~=0.0.21
Requires-Dist: langgraph<1.0.6,>=0.4.2
Requires-Dist: loguru~=0.7.3
Requires-Dist: multidict>6.3.2
Requires-Dist: numpy<2.4.0,>=1.26.4; python_version == '3.11'
Requires-Dist: numpy<2.4.0,>=2.0.0; python_version >= '3.12'
Requires-Dist: onnxruntime<1.24.0,>=1.20.0
Requires-Dist: pandas<2.4.0,>=2.2.3
Requires-Dist: psycopg[binary,pool]~=3.2.4
Requires-Dist: pyarrow>=19.0.1
Requires-Dist: pydantic-settings<2.13.0,>=2.9.1
Requires-Dist: pydantic<2.13.0,>=2.11.1
Requires-Dist: pyowm<3.6,>=3.3
Requires-Dist: python-dotenv<1.3,>=1.1
Requires-Dist: rootutils>=1.0.7
Requires-Dist: setuptools>=75.6.0
Requires-Dist: streamlit<1.52,>=1.45
Requires-Dist: uvicorn<0.39,>=0.35
Requires-Dist: watchdog~=6.0.0
Provides-Extra: all-backends
Requires-Dist: azure-functions<1.25,>=1.23; extra == 'all-backends'
Requires-Dist: gunicorn~=23.0.0; extra == 'all-backends'
Requires-Dist: mangum~=0.19.0; extra == 'all-backends'
Requires-Dist: uvicorn<0.39,>=0.35; extra == 'all-backends'
Provides-Extra: all-llms
Requires-Dist: langchain-anthropic<1.3.1,>=0.3.10; extra == 'all-llms'
Requires-Dist: langchain-aws<1.1.2,>=0.2.20; extra == 'all-llms'
Requires-Dist: langchain-google-genai<4.0.1,>=2.0.0; extra == 'all-llms'
Requires-Dist: langchain-google-vertexai<3.2.1,>=2.0.0; extra == 'all-llms'
Requires-Dist: langchain-openai<1.3.4,>=0.3.15; extra == 'all-llms'
Provides-Extra: all-observability
Requires-Dist: langfuse<3.9.2,>=2.60.3; extra == 'all-observability'
Requires-Dist: langsmith<0.5.0,>=0.3.31; extra == 'all-observability'
Provides-Extra: anthropic
Requires-Dist: langchain-anthropic<1.3.1,>=0.3.10; extra == 'anthropic'
Provides-Extra: aws
Requires-Dist: langchain-aws<1.1.2,>=0.2.20; extra == 'aws'
Provides-Extra: aws-backend
Requires-Dist: mangum~=0.19.0; extra == 'aws-backend'
Provides-Extra: azure-backend
Requires-Dist: azure-functions<1.25,>=1.23; extra == 'azure-backend'
Provides-Extra: google-genai
Requires-Dist: langchain-google-genai<4.0.1,>=2.0.0; extra == 'google-genai'
Provides-Extra: google-vertexai
Requires-Dist: langchain-google-vertexai<3.2.1,>=2.0.0; extra == 'google-vertexai'
Provides-Extra: gunicorn-backend
Requires-Dist: gunicorn~=23.0.0; extra == 'gunicorn-backend'
Requires-Dist: uvicorn[standard]<0.39,>=0.35; extra == 'gunicorn-backend'
Provides-Extra: langfuse
Requires-Dist: langfuse<3.9.2,>=2.60.3; extra == 'langfuse'
Provides-Extra: langsmith
Requires-Dist: langsmith<0.5.0,>=0.3.31; extra == 'langsmith'
Provides-Extra: openai
Requires-Dist: langchain-openai<1.3.4,>=0.3.15; extra == 'openai'
Provides-Extra: uvicorn-backend
Requires-Dist: uvicorn<0.39,>=0.35; extra == 'uvicorn-backend'
